flask_openheart/__init__.py
flask_openheart/config.py
flask_openheart/controller.py
flask_openheart/extension.py
flask_openheart/internal/__init__.py
flask_openheart/internal/backend.py
flask_openheart/internal/keystore.py
flask_openheart/internal/sqlite.py
flask_openheart/internal/storage.py
flask_openheart-0.0.1.dist-info/METADATA
flask_openheart-0.0.1.dist-info/WHEEL
flask_openheart-0.0.1.dist-info/licenses/LICENSE.txt
flask_openheart-0.0.1.dist-info/RECORD
