Metadata-Version: 2.4
Name: flask-openheart
Version: 0.0.1
Summary: A Flask extension to add support for the OpenHeart protocol
Project-URL: Documentation, https://flask-openheart.readthedocs.io/
Project-URL: Repository, https://github.com/woodrowbarlow/flask-openheart/
Author: Woodrow Barlow
License:                     GNU GENERAL PUBLIC LICENSE
License-File: LICENSE.txt
Classifier: Development Status :: 2 - Pre-Alpha
Classifier: Environment :: Web Environment
Classifier: Framework :: Flask
Classifier: Intended Audience :: Developers
Classifier: License :: OSI Approved :: GNU General Public License v3 (GPLv3)
Classifier: Operating System :: OS Independent
Classifier: Programming Language :: Python :: 3
Classifier: Topic :: Internet :: WWW/HTTP :: Dynamic Content
Requires-Python: >=3.8
Requires-Dist: emoji>=2.14.1
Requires-Dist: flask>=2.3
Requires-Dist: werkzeug>=2.3.2
